[
{
	"value":"UNIVERSIDAD DEL ROSARIO - UROSARIO"
},
{
"value":"UNIVERSIDAD CENTRAL COLOMBIA - UCENTRAL"
},
{
"value":"FUNDACION UNIVERSIDAD DE AMERICA - UAMERICA"
},
{
"value":"UNIVERSIDAD EAN (ESCUELA DE ADMINISTRACION DE NEGOCIOS) - EAN"
},
{
"value":"UNIVERSIDAD COLEGIO MAYOR DE CUNDINAMARCA - UNICOLMAYOR"},
{
"value":"UNIVERSIDAD ANTONIO NARIÑO - UAN"},
{
"value":"FUNDACION UNIVERSIDAD AUTONOMA DE COLOMBIA - FUAC"},
{
"value":"UNIVERSIDAD CATOLICA DE COLOMBIA - UCATOLICA"},
{
"value":"UNIVERSIDAD LA GRAN COLOMBIA - UGC"},
{
"value":"INTERNATIONAL TEST OF ENGLISH PROFICIENCY (ITEP) - ITEP"},
{
"value":"UNIVERSIDAD DE LA SALLE - LASALLE"},
{
"value":"UNIVERSIDAD PEDAGOGICA NACIONAL"},
{
"value":"UNIVERSIDAD DE BOGOTA JORGE TADEO LOZANO - UTADEO"},
{
"value":"UNIVERSIDAD EL BOSQUE"},
{
"value":"UNIVERSIDAD EXTERNADO DE COLOMBIA - UEXTERNADO"},
{
"value":"UNIVERSIDAD PILOTO DE COLOMBIA - UNIPILOTO"},
{
"value":"UNIVERSIDAD DE CUNDINAMARCA - UDEC"},
{
"value":"UNIVERSIDAD DE CIENCIAS APLICADAS Y AMBIENTALES - UDCA"},
{
"value":"UNIVERSIDAD LIBRE - UNILIBRE"},
{
"value":"UNIVERSIDAD DEL SINU"},
{
"value":"UNIVERSIDAD DE LA SABANA - UNISABANA"},
{
"value":"UNIVERSIDAD INCCA DE COLOMBIA - INCCA"},
{
"value":"UNIVERSIDAD MILITAR NUEVA GRANADA - UMNG"},
{
"value":"UNIVERSIDAD SERGIO ARBOLEDA - USERGERIO"},
{
"value":"UNIVERSIDAD DISTRITAL FRANCISCO JOSE DE CALDAS - UDISTRITAL"},
{
"value":"UNIVERSIDAD NACIONAL ABIERTA Y A DISTANCIA - UNAD"},
{
"value":"ESCUELA COLOMBIANA DE INGENIERIA JULIO GARAVITO - ESCUELAING"},
{
"value":"DIRECCION NACIONAL DE ESCUELAS DE LA POLICIA NACIONAL - DINAE"},
{
"value":"INSTITUTO CARO Y CUERVO - CAROYCUERVO"},
{
"value":"FUNDACION UNIVERSITARIA DEL AREA ANDINA - AREAANDINDA"},
{
"value":"FUNDACION UNIVERSITARIA DE CIENCIAS DE LA SALUDFUCS"},
{
"value":"CORPORACION UNIVERSITARIA MINUTO DE DIOSUNIMINUTO"},
{
"value":"UNIVERSIDAD CES (CORPORACION PARA ESTUDIOS EN LA SALUD) - CES"},
{
"value":"UNIVERSIDAD DE ANTIOQUIA - UDEA"},
{
"value":"UNIVERSIDAD EAFIT - EAFIT"},
{
"value":"UNIVERSIDAD DE MEDELLIN - UDEM"},
{
"value":"UNIVERSIDAD EIA (ESCUELA DE INGENIERIA DE ANTIOQUIA) - EIA"},
{
"value":"TECNOLOGICO DE ANTIOQUIA INSTITUCION UNIVERSITARIA - TDEA"},
{
"value":"UNIVERSIDAD TECNOLOGICA DEL CHOCO DIEGO LUIS CORDOBA - UTCH"},
{
"value":"UNIVERSIDAD CATOLICA DE ORIENTE - UCO"},
{
"value":"UNIVERSIDAD CATOLICA LUIS AMIGO - FUNLAM"},
{
"value":"UNIVERSIDAD AUTONOMA DEL CARIBE - UAC"},
{
"value":"UNIVERSIDAD DE CORDOBA - UNICORDOBA"},
{
"value":"UNIVERSIDAD DE CARTAGENA - UNICARTAGENA"},
{
"value":"CORPORACION UNIVERSIDAD DE LA COSTA - CUC"},
{
"value":"UNIVERSIDAD TECNOLOGICA DE BOLIVAR - UTB"},
{
"value":"UNIVERSIDAD SIMON BOLIVAR - USB"},
{
"value":"UNIVERSIDAD METROPOLITANA - UNIMETRO"},
{
"value":"UNIVERSIDAD DEL SINU ELIAS BECHARA ZAINUM - UNISINU"},
{
"value":"ESCUELA NAVAL DE CADETES ALMIRANTE PADILLA"},
{
"value":"UNIVERSIDAD DEL MAGDALENA - MAGDALENA"},
{
"value":"UNIVERSIDAD DEL ATLANTICO - ATLANTICO"},
{
"value":"UNIVERSIDAD DEL NORTE - NORTE"},
{
"value":"ESCUELA MILITAR DE AVIACION MARCO FIDEL SUAREZ - EMAVI"},
{
"value":"UNIVERSIDAD DEL CAUCA - CAUCA"},
{
"value":"UNIVERSIDAD MARIANA - MARIANA"},
{
"value":"UNIVERSIDAD AUTONOMA DE OCCIDENTE - UAO"},
{
"value":"UNIVERSIDAD DEL VALLE - VALLE"},
{
"value":"UNIVERSIDAD SANTIAGO DE CALI - USC"},
{
"value":"UNIVERSIDAD DE NARIÑO - UDENAR"},
{
"value":"UNIVERSIDAD ICESI - ICESI"},
{
"value":"UNIVERSIDAD AUTONOMA DE MANIZALES - UAM"},
{
"value":"UNIVERSIDAD DE CALDAS - CALDAS"},
{
"value":"UNIVERSIDAD DE LA AMAZONIA"},
{
"value":"UNIVERSIDAD SURCOLOMBIANA - USCO"},
{
"value":"UNIVERSIDAD CATOLICA DE MANIZALES - UCM"},
{
"value":"UNIVERSIDAD DE IBAGUE - BAGUE"},
{
"value":"UNIVERSIDAD DEL QUINDIO - QUINDIO"},
{
"value":"UNIVERSIDAD TECNOLOGICA DE PEREIRA - UTP"},
{
"value":"UNIVERSIDAD CATOLICA DE PEREIRA - UCP"},
{
"value":"UNIVERSIDAD DE MANIZALES - MANIZALES"},
{
"value":"UNIVERSIDAD DEL TOLIMA - TOLIMA"},
{
"value":"CORPORACION UNIVERSITARIA DEL META - META"},
{
"value":"UNIVERSIDAD DE PAMPLONA - PAMPLONA"},
{
"value":"UNIVERSIDAD INDUSTRIAL DE SANTANDER - UIS"},
{
"value":"UNIVERSIDAD AUTONOMA DE BUCARAMANGA - UNAB"},
{
"value":"UNIVERSIDAD DE SANTANDER - UDES"},
{
"value":"UNIVERSIDAD FRANCISCO DE PAULA SANTANDER - UFPS"},
{
"value":"UNIVERSIDAD DE BOYACA - UB"},
{
"value":"UNIVERSIDAD DE LOS LLANOS - UNILLANOS"},
{
"value":"UNIVERSIDAD PEDAGOGICA Y TECNOLOGICA DE COLOMBIA - UPTC"},
{
"value":"UNIVERSIDAD DE LA GUAJIRA"},
{
"value":"UNIVERSIDAD DE SUCRE - UNISUCRE"},
{
"value":"ESCUELA SUPERIOR DE ADMINISTRACION PUBLICA - ESAP"},
{
"value":"FUNDACION UNIVERSITARIA LOS LIBERTADORES - ULIBERTADORES"},
{
"value":"UNIVERSIDAD POPULAR DEL CESAR - UNICESAR"},
{
"value":"INSTITUTO NACIONAL PARA CIEGOSINCI"},
{
"value":"INSTITUTO NACIONAL PARA SORDOS - INSOR"},
{
"value":"ESCUELA TECNOLOGICA INSTITUTO TECNICO CENTRAL - ETITC"},
{
"value":"INSTITUTO TECNICO NACIONAL DE COMERCIO SIMON RODRIGUEZ - INTENALCO"},
{
"value":"INSTITUTO TOLIMENSE DE FORMACION TECNICA PROFESIONAL - ITFIP"},
{
"value":"INSTITUTO NACIONAL DE FORMACION TECNICA PROFESIONAL DE SAN ANDRES Y PROVIDENCIA - INFOTEPSAI"},
{
"value":"UNIVERSIDAD DE LOS ANDES"},
{
"value":"CORPORACION UNIVERSITARIA DE SUCRE CORPOSUCRE - CORPOSUCRE"},
{
"value":"CORPORACION UNIVERSITARIA AUTONOMA DEL CAUCA"},
{
"value":"INSTITUTO TECNOLOGICO METROPOLITANO - ITM"},
{
"value":"FUNDACION UNIVERSITARIA KONRAD LORENZ"},
{
"value":"UNIVERSIDAD COOPERATIVA DE COLOMBIA - UCC"},
{
"value":"CORPORACION EDUCATIVA ITAE - ITAE"},
{
"value":"UNIVERSIDAD MANUELA BELTRAN"},
{
"value":"CORPORACION UNIVERSITARIA DEL CARIBE (CECAR) - CECAR"},
{
"value":"COLEGIO DE ESTUDIOS SUPERIORES DE ADMINISTRACION (CESA) - CESA"},
{
"value":"FUNDACION UNIVERSITARIA CERVANTINA SAN AGUSTIN"},
{
"value":"INSTITUTO TECNOLOGICO SAN AGUSTIN"},
{
"value":"FUNDACION UNIVERSITARIA MARIA CANO - FUMC"},
{
"value":"SERVICIO NACIONAL DE APRENDIZAJE - SENA"},
{
"value":"UNIVERSIDAD DE INVESTIGACION Y DESARROLLO - UDI"},
{
"value":"FUNDACION UNIVERSITARIA MONSERRATE"},
{
"value":"INSTITUCION UNIVERSITARIA COLEGIO MAYOR DE ANTIOQUIA"},
{
"value":"CORPORACION UNIVERSITARIA UNITEC"},
{
"value":"CORPORACION UNIVERSITARIA LASALLISTA"},
{
"value":"UNIVERSIDAD AUTONOMA LATINOAMERICANA"},
{
"value":"ESCUELA COLOMBIANA DE CARRERAS INDUSTRIALES - ECCI"},
{
"value":"INSTITUCION UNIVERSITARIA DE ENVIGADO"},
{
"value":"ESCUELA COLOMBIANA DE REHABILITACION - ECR"},
{
"value":"INSTITUCION TECNOLOGICA COLEGIO MAYOR DE BOLIVAR"},
{
"value":"FUNDACION UNIVERSITARIA CATOLICA DEL NORTE - UCN"},
{
"value":"UNIREMINGTON"},
{
"value":"FUNDACION UNIVERSITARIA JUAN N. CORPAS"},
{
"value":"POLITECNICO COLOMBIANO JAIME ISAZA CADAVID"},
{
"value":"INSTITUCION UNIVERSITARIA LATINA (UNILATINA) - UNILATINA"},
{
"value":"CORPORACION UNIVERSITARIA ADVENTISTA - UNAC"},
{
"value":"FUNDACION DE ESTUDIOS SUPERIORES COMFANORTE - FESC"},
{
"value":"CORPORACION UNIFICADA NACIONAL DE EDUCACION SUPERIOR - CUN"},
{
"value":"CEIPA BUSINESS SCHOOL (CENTRO DE INVESTIGACION Y PLANEAMIENTO ADMINISTRATIVO)"},
{
"value":"INSTITUCION UNIVERSITARIA FUNDACION EDUCATIVA ESUMER"},
{
"value":"UNIDAD CENTRAL DEL VALLE DEL CAUCA"},
{
"value":"FUNDACION UNIVERSITARIA DE POPAYAN - FUP"},
{
"value":"INSTITUTO TECNOLOGICO PASCUAL BRAVO"},
{
"value":"INSTITUCION UNIVERSITARIA COLEGIOS DE COLOMBIA (UNICOC) - UNICOC"},
{
"value":"UNIVERSITARIA AGUSTINIANA"},
{
"value":"FUNDACION UNIVERSITARIA PANAMERICANA"},
{
"value":"FUNDACION UNIVERSITARIA SANITAS (UNISANITAS) - UNISANITAS"},
{
"value":"CORPORACION UNIVERSITARIA DE CIENCIAS EMPRESARIALES, EDUCACION Y SALUD - CORSALUD"},
{
"value":"INSTITUTO TECNOLOGICO DEL PUTUMAYO - ITP"},
{
"value":"CORPORACION UNIVERSITARIA DEL HUILA - CORHUILA"},
{
"value":"INSTITUTO TECNOLOGICO DE SOLEDAD ATLANTICO (ITSA) - ITSA"},
{
"value":"POLITECNICO GRANCOLOMBIANO - POLI"},
{
"value":"INSTITUCION UNIVERSITARIA ANTONIO JOSE CAMACHO"},
{
"value":"FUNDACION UNIVERSITARIA AGRARIA DE COLOMBIA (UNIAGRARIA) - UNIAGRARIA"},
{
"value":"FUNDACION UNIVERSITARIA CATOLICA LUMEN GENTIUM - UNICATOLICA"},
{
"value":"FUNDACION UNIVERSITARIA INTERNACIONAL DEL TROPICO AMERICANO (UNITROPICO) - UNITROPICO"},
{
"value":"FUNDACION UNIVERSITARIA AUTONOMA DE LAS AMERICAS - UAM"},
{
"value":"INALDE BUSINESS SCHOOL (UNIVERSIDAD DE LA SABANA)"},
{
"value":"FUNDACION UNIVERSITARIA TECNOLOGICO COMFENALCO"},
{
"value":"INSTITUCION UNIVERSITARIA CENTRO DE ESTUDIOS SUPERIORES MARIA GORETTI (CESMAG) - CESMAG"},
{
"value":"ESCUELA NACIONAL DEL DEPORTE"},
{
"value":"CORPORACION UNIVERSITARIA REPUBLICANA"},
{
"value":"UNIDADES TECNOLOGICAS DE SANTANDER - UTS"},
{
"value":"CORPORACION UNIVERSITARIA AMERICANA"},
{
"value":"CORPORACION ACADEMIA SUPERIOR DE ARTES"},
{
"value":"FUNDACION UNIVERSITARIA SAN MARTIN"},
{
"value":"INSTITUTO UNIVERSITARIO DE LA PAZ"},
{
"value":"UNIVERSIDAD SAN GIL - UNISANGIL"},
{
"value":"FUNDACION PARA LA EDUCACION SUPERIOR SAN MATEO"},
{
"value":"FUNDACION TECNOLOGICA ANTONIO DE AREVALO - TECNAR"},
{
"value":"INSTITUCION UNIVERSITARIA SALAZAR Y HERRERA - IUSH"},
{
"value":"FUNDACION TECNOLOGICA LIDERAZGO CANADIENSE INTERNACIONAL - LCI"},
{
"value":"ESCUELA MILITAR DE CADETES GENERAL JOSE MARIA CORDOVA"},
{
"value":"CORPORACION UNIVERSITARIA DE CIENCIA Y TECNOLOGIA DE COLOMBIA"},
{
"value":"CORPORACION UNIVERSITARIA DE CIENCIA Y DESARROLLO"},
{
"value":"CORPORACION UNIVERSITARIA COMFACAUCA"},
{
"value":"ESCUELA DE ADMINISTRACION Y MERCADOTECNIA DEL QUINDIO - EAM"},
{
"value":"CORPORACION UNIVERSITARIA DE SABANETA J. EMILIO VALDERRAMA (UNISABANETA)"},
{
"value":"FUNDACION UNIVERSITARIA BELLAS ARTES MEDELLIN"},
{
"value":"INSTITUTO DEPARTAMENTAL DE BELLAS ARTES"},
{
"value":"FUNDACION UNIVERSITARIA CAFAM"},
{
"value":"CORPORACION UNIVERSITARIA RAFAEL NUÑEZ - CURN"},
{
"value":"INSTITUTO DE EDUCACION TECNICA PROFESIONAL DE ROLDANILLO - INTEP"},
{
"value":"CORPORACION COLEGIATURA COLOMBIANA"},
{
"value":"INSTITUTO NACIONAL DE FORMACION TECNICA PROFESIONAL HUMBERTO VELASQUEZ GARCIA - INFOTEPHVG"},
{
"value":"CORPORACION UNIVERSITARIA DE SANTA ROSA DE CABAL - UNISARC"},
{
"value":"CORPORACION DE ESTUDIOS TECNOLOGICOS DEL NORTE DEL VALLE"},
{
"value":"FUNDACION UNIVERSITARIA EMPRESARIAL DE LA CAMARA DE COMERCIO DE BOGOTA - UNIEMPRESARIAL"},
{
"value":"FUNDACION EDUCATIVA CESDE"},
{
"value":"CONSERVATORIO DEL TOLIMA"},
{
"value":"FUNDACION ACADEMIA DE DIBUJO PROFESIONAL - FADP"},
{
"value":"SALAMANDRA CORPORACION DE ESTUDIOS SUPERIORES"},
{
"value":"ESCUELA SUPERIOR DE GUERRA"},
{
"value":"FUNDACION UNIVERSITARIA JUAN DE CASTELLANOS - JDC"},
{
"value":"INSTITUCION UNIVERSITARIA ESCOLME FUNDACION ESCUELA COLOMBIANA DE MERCADOTECNIA"},
{
"value":"CORPORACION UNIVERSITARIA CENDA"},
{
"value":"FUNDACION UNIVERSITARIA CLARETIANA (UNICLARETIANA) - FUCLA"},
{
"value":"INSTITUCION UNIVERSITARIA CORPORACION ESCUELA DE ARTES Y LETRAS"},
{
"value":"POLITECNICO DE LA COSTA ATLANTICA - PCA"},
{
"value":"CORPORACION INTERNACIONAL PARA EL DESARROLLO EDUCATIVO - CIDE"},
{
"value":"FUNDACION UNIVERSITARIA NAVARRA"},
{
"value":"CORPORACION UNIVERSITARIA AUTONOMA DE NARIÑO - AUNAR"},
{
"value":"INSTITUCION UNIVERSITARIA COLEGIO MAYOR DEL CAUCA"},
{
"value":"CORPORACION EDUCATIVA TALLER 5 CENTRO DE DISEÑO"},
{
"value":"POLITECNICO INTERNACIONAL INSTITUCION DE EDUCACION SUPERIOR"},
{
"value":"INSTITUCION UNIVERSITARIA BELLAS ARTES Y CIENCIAS DE BOLIVAR - UNIBAC"},
{
"value":"CORPORACION UNIVERSITARIA REFORMADA"},
{
"value":"CENTRO DE INVESTIGACION DOCENCIA Y CONSULTORIA ADMINISTRATIVA - CIDCA"},
{
"value":"INSTITUTO SUPERIOR DE EDUCACION RURAL - ISER"},
{
"value":"CENTRO COLOMBIANO DE ESTUDIOS PROFESIONALES - CECEP"},
{
"value":"FUNDACION UNIVERSITARIA PARA EL DESARROLLO HUMANO (UNINPAHU) - UNIPAHU"},
{
"value":"INSTITUCION UNIVERSITARIA COLOMBO AMERICANA - UNICA"},
{
"value":"CORPORACION INSTITUTO SUPERIOR DE EDUCACION SOCIAL - ISES"},
{
"value":"FUNDACION UNIVERSITARIA SEMINARIO BIBLICO DE COLOMBIA - UNISBC"},
{
"value":"CORPORACION UNIVERSITARIA LATINOAMERICANA - CUL"},
{
"value":"POLITECNICO COLOMBO ANDINO - POLCOLAN"},
{
"value":"CORPORACION UNIVERSITARIA ASTURIAS"},
{
"value":"CORPORACION UNIVERSITARIA IBEROAMERICANA - IBERO"},
{
"value":"FUNDACION ESCUELA COLOMBIANA DE HOTELERIA Y TURISMO (ECOTET) - ECOTET"},
{
"value":"CENTRO DE EDUCACION MILITAR - CEMIL"},
{
"value":"ESCUELA DE INTELIGENCIA Y CONTRAINTELIGENCIA - ESICI"},
{
"value":"ESCUELA DE SUBOFICIALES DE LA FUERZA AEREA COLOMBIANA ANDRES M. DIAZ"},
{
"value":"CORPORACION TECNOLOGICA DE BOGOTA - CTB"},
{
"value":"ESCUELA DE INGENIEROS MILITARES - ESING"},
{
"value":"ESCUELA MILITAR DE SUBOFICIALES SARGENTO INOCENCIO CHINCA - EMSUB"},
{
"value":"UNICOLOMBIA"},
{
"value":"FUNDACION UNIVERSITARIA COLOMBO INTERNACIONAL - UNICOLOMBO"},
{
"value":"FUNDACION UNIVERSITARIA DEL ESPINAL"},
{
"value":"CORPORACION UNIVERSITARIA DE COLOMBIA IDEAS"},
{
"value":"CORPORACION CENTRO DE ESTUDIOS ARTISTICOS Y TECNICOS - CE-ART"},
{
"value":"UNIVERSITARIA VIRTUAL INTERNACIONAL"},
{
"value":"TECNOLOGICA INDUSTRIAL COLOMBIANA - TEINCO"},
{
"value":"CORPORACION UNIVERSITARIA EMPRESARIAL DE SALAMANCA - CUES"},
{
"value":"CORPORACION UNIVERSAL DE INVESTIGACION Y TECNOLOGIA (CORUNIVERSITEC) - CORUNIVERSITEC"},
{
"value":"FUNDACION UNIVERSITARIA SAN ALFONSO"},
{
"value":"CORPORACION UNIVERSITARIA CENTRO SUPERIOR (UNICUCES) - UNICUCES"},
{
"value":"FUNDACION TECNOLOGICA AUTONOMA DE BOGOTA - FABA"},
{
"value":"COLEGIO INTEGRADO NACIONAL ORIENTE DE CALDAS - IES CINOC"},
{
"value":"ESCUELA DE TECNOLOGIAS DE ANTIOQUIA - ETDEA"},
{
"value":"ESCUELA DE COMUNICACIONES MILITARES - ESCOM"},
{
"value":"INSTITUTO TECNICO AGRICOLA - ITA"},
{
"value":"CORPORACION DE EDUCACION TECNOLOGICA COLSUBSIDIO - CET COLSUBSIDIO"},
{
"value":"INSTITUTO SUPERIOR DE CIENCIAS SOCIALES Y ECONOMICO FAMILIARES - ICSEF"},
{
"value":"FUNDACION DE EDUCACION SUPERIOR SAN JOSE"},
{
"value":"ESCUELA SUPERIOR TECNOLOGICA DE ARTES DEBORA ARANGO"},
{
"value":"FUNDACION DE ESTUDIOS SUPERIORES UNIVERSITARIOS DE URABA - FESU"},
{
"value":"INSTITUCION UNIVERSITARIA MARCO FIDEL SUAREZ"},
{
"value":"TECNOLOGICA FITEC"},
{
"value":"CORPORACION ACADEMIA TECNOLOGICA DE COLOMBIA (ATEC) - ATEC"},
{
"value":"CORPORACION REGIONAL DE EDUCACION SUPERIOR (CRES)"},
{
"value":"ESCUELA DE POSGRADOS DE LA FUERZA AEREA COLOMBIANA - FAC"},
{
"value":"CORPORACION INSTITUTO DE ADMINISTRACION Y FINANZAS - CIAF"},
{
"value":"FUNDACION TECNOLOGICA COLOMBO GERMANA"},
{
"value":"INSTITUCION TECNOLOGICA CEDESISTEMAS"},
{
"value":"ESCUELA TECNOLOGICA DEL ORIENTE"},
{
"value":"TECNOLOGICA AUTONOMA DEL PACIFICO - UTAP"},
{
"value":"FUNDACION DE EDUCACION SUPERIOR NUEVA AMERICA"},
{
"value":"CORPORACION DE EDUCACION DEL NORTE DEL TOLIMA"},
{
"value":"FUNDACION UNIVERSITARIA CIEO UNICIEO - UNICIEO"},
{
"value":"CORPORACION TECNOLOGICA CATOLICA DE OCCIDENTE - TECOC"},
{
"value":"CORPORACION ESCUELA SUPERIOR DE ADMINISTRACION Y ESTUDIOS TECNOLOGICOS - EAE"},
{
"value":"FUNDACION UNIVERSITARIA COMFENALCO SANTANDER - UNC"},
{
"value":"FUNDACION INTERAMERICANA TECNICA - FIT"},
{
"value":"UNIVERSIDAD BAUTISTA CALI"},
{
"value":"FUNDACION ESCUELA TECNOLOGICA DE NEIVA JESUS OVIEDO PEREZ"},
{
"value":"ESCUELA LATINOAMERICANA DE INGENIEROS TECNOLOGOS Y EMPRESARIOS (ELITE) - ELITE"},
{
"value":"CORPORACION INTERAMERICANA DE EDUCACION SUPERIOR"},
{
"value":"FUNDACION CENTRO DE EDUCACION SUPERIOR INVESTIGACION Y PROFESIONALIZACION - CEDINPRO"},
{
"value":"FUNDACION TECNOLOGICA ALBERTO MERANI"},
{
"value":"INSTITUTO DE EDUCACION EMPRESARIAL (IDEE) - IDEE"},
{
"value":"CORPORACION INSTITUTO COLOMBO ALEMAN PARA LA FORMACION TECNOLOGICA - CAFT"},
{
"value":"FUNDACION POLITECNICA CORPO EDUCACION SUPERIOR EN ESTETICA"},
{
"value":"ESCUELA SUPERIOR DE CIENCIAS EMPRESARIALES - ECIEM"},
{
"value":"FUNDACION TECNOLOGICA DE MADRID - FTM"},
{
"value":"CORPORACION UNIVERSITARIA PARA EL DESARROLLO EMPRESARIAL Y SOCIAL (CUDES) - CUDES"},
{
"value":"UNION AMERICANA DE EDUCACION SUPERIOR - UNAES"},
{
"value":"FUNDACION CENTRO UNIVERSITARIO DE BIENESTAR RURAL - CUBR"},
{
"value":"CORPORACION TECNOLOGICA INDOAMERICA"},
{
"value":"TECNOLOGICA DEL SUR (TECNOLOGICA DANIEL GUILLARD)"},
{
"value":"INSTITUCION UNIVERSITARIA DE COLOMBIA"},
{
"value":"TECNOLOGICO DE ENERGIA E INNOVACION E-LERNOVA"},
{
"value":"ESCUELA DE LOGISTICA"},
{
"value":"INSTITUTO TECNOLOGICO DE SUR"},
{
"value":"FUNDACION TECNOLOGICA RURAL COREDI (FUNTEC) - COREDI"},
{
"value":"POLITECNICO SANTAFE DE BOGOTA"},
{
"value":"POLITECNICO INDOAMERICANO"},
{
"value":"SURAMERICA EDUCACION SUPERIOR"},
{
"value":"CORPORACION INTERAMERICANA DE EDUCACION - CIDES"},
{
"value":"UNIVERSIDAD SANTO TOMAS - USTA"},
{
"value":"UNIVERSIDAD DE SAN BUENAVENTURA - USB"},
{
"value":"UNIVERSIDAD PONTIFICIA BOLIVARIANA - UPB"},
{
"value":"PONTIFICIA UNIVERSIDAD JAVERIANA - PUJ"},
{
"value":"UNIVERSIDAD NACIONAL DE COLOMBIA - UNAL"},
{
"value":"CORPORACION EDUCATIVA DEL LITORAL - CEL"},
{
"value":"CORPORACION DE EDUCACION SUPERIOR MIGUEL CAMACHO PEREA"},
{
"value":"CORPORACION DE EDUCACION DEL ORIENTE"},
{
"value":"FUNDACION PARA LA EDUCACION SUPERIOR REAL DE COLOMBIA"},
{
"value":"INSTITUTO BIBLICO PATRICIO SYMES"},
{
"value":"FUNDACION UNIVERSITARIA - FUNDACION CARDIOVASCULAR DE COLOMBIA (FCV) - FCV"},
{
"value":"INSTITUTO TECNOLOGICO DE ELECTRONICO Y COMUNICACIONES (ITEC) - ITEC"},
{
"value":"FUNDACION UNIVERSITARIA INTERNACIONAL DE LA RIOJA (UNIR) - UNIR"},
{
"value":"UNIDAD TECNICA PROFESIONAL DE SEVILLA (UNITEPS) - UNITEPS"},
{
"value":"INSTITUCION UNIVERSITARIA CONOCIMIENTO E INNOVACION PARA LA JUSTICIA (CIJ) - CIJ"},
{
"value":"INSTITUCION UNIVERSITARIA DIGITAL DE ANTIOQUIA (UDIGITAL) - UDIGITAL"},
{
"value":"ESCUELA SUPERIOR DE OFTALMOLOGIA - INSTITUTO BARRAQUER DE AMERICA"},
{
"value":"CORPORACION BOLIVARIANA DE EDUCACION SUPERIOR (CORBES) - CORBES"},
{
"value":"CORPORACION TECNICA DE COLOMBIA - CORPOTEC"},
{
"value":"INSTITUCION UNIVERSITARIA COMANDO DE EDUCACION Y DOCTRINA (CEDOC) - CEDOC"},
{
"value":"FUNDACION DE EDUCACION SUPERIOR (ESATEC) - ESATEC"},
{
"value":"FUNDACION EUROCOLOMBIANA DE EDUCACION SUPERIOR"},
{
"value":"FUNDACION INSTITUTO DE CARRERAS TECNICAS PROFESIONALES (FIDCI) - FIDCI"},
{
"value":"FUNDACION UNIVERSITARIA HORIZONTE"},
{
"value":"CORPORACION JOHN F KENNEDY"},
{
"value":"FUNDACION UNIVERSITARIA SALESIANA"},
{
"value":"UNIVERSIDAD AUTONOMA INDIGENA INTERCULTURAL (UAIIN) - UAIIN"},
{
"value":"FUNDACION UNIVERSITARIA COMFAMILIAR RISARALDA"},
{
"value":"CORPORACION UNIVERSITARIA DE CATALUÑA - UC"},
{
"value":"FUNDACION UNIVERSITARIA LUIS G. PAEZ - UNILUISGPAEZ"},
{
"value":"FUNDACION UNIVERSITARIA INTERNACIONAL DE COLOMBIA - UNINCOL"},
{
"value":"CORPORACION EDUCATIVA ALEXANDER VON HUMBOLDT"},
{
"value":"IMF BUSINESS SCHOOL - IMF"},
{
"value":"CORPORACION TECNOLOGICO COPACABANA (TECO) - TECO"},
{
"value":"CORPORACION PARA INVESTIGACIONES BIOLOGICASCIB"},
{
"value":"POLITECNICO DE ANTIOQUIA"},
{
"value":"CENTRO DE COMERCIO REGIONAL ANTIOQUIA"},
{
"value":"ESCUELA NAVAL DE SUBOFICIALES ARC BARRANQUILLA - ARC"},
{
"value":"CORPORACION UNIVERSITARIA REGIONAL DEL CARIBE (IAFIC)"},
{
"value":"INSTITUTO TECNICO DE COLOMBIA - POR COMPETENCIAS S.A.S"},
{
"value":"INSTITUTO CENIS DE COLOMBIA"},
{
"value":"ACADEMIA NACIONAL DE APRENDIZAJE"},
{
"value":"CENTRO COLOMBIANO AMERICANO DE MEDELLIN"},
{
"value":"FUNDACION UNIVERSITARIA TECNOLOGICA DE CASANARE (FUC)  - FUTC"},
{
"value":"CORPORACION CENTRO TECNICO ARQUITECTONICO (CTA) (PEREIRA)"},
{
"value":"ESCUELA DE FORMACION DE INFANTERIA DE MARINA (EFIM) - EFIM"},
{
"value":"UNIVERSIDAD DEL PACIFICO"},
{
"value":"CENTRO INTERNACIONAL DE ENTRENAMIENTO E INVESTIGACIONES MEDICAS (CIDEIM) - CIDEIM"},
{
"value":"ESCUELA DE SUBOFICIALES DE LA FUERZA AEREA COLOMBIANA (ESUFA) - ESUFA"},
{
"value":"CORPORACION POLITECNICO DE CUNDINAMARCA"},
{
"value":"FUNDACION EDUCATIVA COMERCIAL (FUNDEC) - FUNDEC"},
{
"value":"FUNDACION EDUCATIVA SAN JUAN BAUTISTA"},
{
"value":"INSTITUTO NACIONAL DE FORMACION TECNICA PROFESIONAL (INFOTEP) - INFOTEP"},
{
"value":"INSTITUTO POLITECNICO AGRO INDUSTRIAL (ACACIAS)"},
{
"value":"CORPORACION UNIVERSITARIA EMPRESARIAL ALEXANDER VON HUMBOLDT (CUE) - CUE"},
{
"value":"FUNDACION AUTONOMA DE SANTANDER (FAS) - FAS"},
{
"value":"MULTITECH CENTRO DE EDUCACION PARA EL TRABAJO"},
{
"value":"INSTITUTO MULTICOMPUTO SANTANDER"},
{
"value":"FUNDACION EDUCATIVA DEL ORIENTE COLOMBIANO"},
{
"value":"CORPORACION UNIVERSITARIA DE LOS ANDES - CUA"
}
]
